{
  "kind": "CustomResourceDefinition",
  "apiVersion": "core.nrc.no/v1",
  "metadata": {
    "name": "blas.bla.com"
  },
  "spec": {
    "group": "bla.com",
    "names": {
      "kind": "Bla",
      "plural": "blas",
      "singular": "bla"
    },
    "versions": [
      {
        "name": "v1",
        "storage": true,
        "served": true,
        "schema": {
          "openAPIV3Schema": {
            "type": "object",
            "properties": {
              "kind": {
                "type": "string"
              },
              "apiVersion": {
                "type": "string"
              },
              "spec": {
                "type": "object",
                "properties": {
                  "firstName": {
                    "type": "string"
                  },
                  "lastName": {
                    "type": "string"
                  }
                }
              }
            }
          }
        }
      }
    ]
  }
}